polyagamma/__init__.pxd
polyagamma/__init__.py
polyagamma/__init__.pyi
polyagamma/_polyagamma.cpython-310-x86_64-linux-gnu.so
polyagamma/_polyagamma.pxd
polyagamma/_polyagamma.pyi
polyagamma/_version.py
polyagamma-2.0.2.dist-info/METADATA
polyagamma-2.0.2.dist-info/WHEEL
polyagamma-2.0.2.dist-info/top_level.txt
polyagamma-2.0.2.dist-info/RECORD
polyagamma-2.0.2.dist-info/licenses/LICENSE
