Metadata-Version: 2.4
Name: polyagamma
Version: 2.0.2
Summary: Efficiently generate samples from the Polya-Gamma distribution using a NumPy/SciPy compatible interface.
Author-email: Zolisa Bleki <zolisa.bleki@gmail.com>
License: BSD 3-Clause License
Project-URL: source, https://github.com/zoj613/polyagamma
Project-URL: tracker, https://github.com/zoj613/polyagamma/issues
Keywords: polya-gamma distribution,polya-gamma random sampling
Classifier: Intended Audience :: Science/Research
Classifier: Topic :: Scientific/Engineering
Classifier: License :: OSI Approved :: BSD License
Classifier: Programming Language :: C
Classifier: Programming Language :: Python
Classifier: Programming Language :: Python :: 3 :: Only
Classifier: Operating System :: POSIX :: Linux
Classifier: Operating System :: Microsoft :: Windows :: Windows 10
Classifier: Operating System :: MacOS :: MacOS X
Classifier: Typing :: Typed
Requires-Python: >=3.10
License-File: LICENSE
Requires-Dist: numpy>=1.19.0
Dynamic: license-file
